[
  {
    "ContainingType": "ShoesStore_Project.Controllers.BasketController",
    "Method": "AddToBasket",
    "RelativePath": "api/Basket/AddToBasket",
    "HttpMethod": "POST",
    "IsController": true,
    "Order": 0,
    "Parameters": [
      {
        "Name": "basketDTO",
        "Type": "Interfaces.DTOs.Basket_DTOs.Add_ChangeToBasketDTO",
        "IsRequired": true
      }
    ],
    "ReturnTypes": [
      {
        "Type": "System.Void",
        "MediaTypes": [],
        "StatusCode": 204
      },
      {
        "Type": "Microsoft.AspNetCore.Mvc.ProblemDetails",
        "MediaTypes": [
          "text/plain",
          "application/json",
          "text/json"
        ],
        "StatusCode": 400
      },
      {
        "Type": "System.Void",
        "MediaTypes": [],
        "StatusCode": 500
      }
    ]
  },
  {
    "ContainingType": "ShoesStore_Project.Controllers.BasketController",
    "Method": "ChangeBasketItemQuantity",
    "RelativePath": "api/Basket/ChangeBasketItemQuantity",
    "HttpMethod": "PUT",
    "IsController": true,
    "Order": 0,
    "Parameters": [
      {
        "Name": "basketDTO",
        "Type": "Interfaces.DTOs.Basket_DTOs.Add_ChangeToBasketDTO",
        "IsRequired": true
      }
    ],
    "ReturnTypes": [
      {
        "Type": "System.Void",
        "MediaTypes": [],
        "StatusCode": 204
      },
      {
        "Type": "Microsoft.AspNetCore.Mvc.ProblemDetails",
        "MediaTypes": [
          "text/plain",
          "application/json",
          "text/json"
        ],
        "StatusCode": 400
      },
      {
        "Type": "System.Void",
        "MediaTypes": [],
        "StatusCode": 500
      }
    ]
  },
  {
    "ContainingType": "ShoesStore_Project.Controllers.BasketController",
    "Method": "DeleteAllBasketItem",
    "RelativePath": "api/Basket/DeleteAllBasketItem",
    "HttpMethod": "DELETE",
    "IsController": true,
    "Order": 0,
    "Parameters": [],
    "ReturnTypes": [
      {
        "Type": "System.Void",
        "MediaTypes": [],
        "StatusCode": 204
      },
      {
        "Type": "Microsoft.AspNetCore.Mvc.ProblemDetails",
        "MediaTypes": [
          "text/plain",
          "application/json",
          "text/json"
        ],
        "StatusCode": 400
      },
      {
        "Type": "System.Void",
        "MediaTypes": [],
        "StatusCode": 500
      }
    ]
  },
  {
    "ContainingType": "ShoesStore_Project.Controllers.BasketController",
    "Method": "GetBasketPaged",
    "RelativePath": "api/Basket/GetBasketPaged",
    "HttpMethod": "GET",
    "IsController": true,
    "Order": 0,
    "Parameters": [
      {
        "Name": "pageNumber",
        "Type": "System.Int32",
        "IsRequired": false
      },
      {
        "Name": "pageSize",
        "Type": "System.Int32",
        "IsRequired": false
      }
    ],
    "ReturnTypes": [
      {
        "Type": "System.Void",
        "MediaTypes": [],
        "StatusCode": 204
      },
      {
        "Type": "Microsoft.AspNetCore.Mvc.ProblemDetails",
        "MediaTypes": [
          "text/plain",
          "application/json",
          "text/json"
        ],
        "StatusCode": 400
      },
      {
        "Type": "System.Void",
        "MediaTypes": [],
        "StatusCode": 500
      }
    ]
  },
  {
    "ContainingType": "ShoesStore_Project.Controllers.BrandController",
    "Method": "AddNewBrand",
    "RelativePath": "api/Brand/AddNewBrand",
    "HttpMethod": "POST",
    "IsController": true,
    "Order": 0,
    "Parameters": [
      {
        "Name": "brand",
        "Type": "Interfaces.DTOs.BrandDTO",
        "IsRequired": true
      }
    ],
    "ReturnTypes": [
      {
        "Type": "System.Int32",
        "MediaTypes": [
          "text/plain",
          "application/json",
          "text/json"
        ],
        "StatusCode": 200
      },
      {
        "Type": "Microsoft.AspNetCore.Mvc.ProblemDetails",
        "MediaTypes": [
          "text/plain",
          "application/json",
          "text/json"
        ],
        "StatusCode": 400
      },
      {
        "Type": "System.Void",
        "MediaTypes": [],
        "StatusCode": 500
      }
    ]
  },
  {
    "ContainingType": "ShoesStore_Project.Controllers.BrandController",
    "Method": "GetBrands",
    "RelativePath": "api/Brand/GetBrands",
    "HttpMethod": "GET",
    "IsController": true,
    "Order": 0,
    "Parameters": [],
    "ReturnTypes": [
      {
        "Type": "System.Collections.Generic.IEnumerable\u00601[[Interfaces.DTOs.BrandDTO, Interfaces, Version=1.0.0.0, Culture=neutral, PublicKeyToken=null]]",
        "MediaTypes": [
          "text/plain",
          "application/json",
          "text/json"
        ],
        "StatusCode": 200
      },
      {
        "Type": "System.Void",
        "MediaTypes": [],
        "StatusCode": 500
      }
    ]
  },
  {
    "ContainingType": "ShoesStore_Project.Controllers.CategoriesController",
    "Method": "GetCategories",
    "RelativePath": "api/Categories/GetCategories",
    "HttpMethod": "GET",
    "IsController": true,
    "Order": 0,
    "Parameters": [],
    "ReturnTypes": [
      {
        "Type": "System.Collections.Generic.IEnumerable\u00601[[Interfaces.DTOs.CategoryDTO, Interfaces, Version=1.0.0.0, Culture=neutral, PublicKeyToken=null]]",
        "MediaTypes": [
          "text/plain",
          "application/json",
          "text/json"
        ],
        "StatusCode": 200
      },
      {
        "Type": "System.Void",
        "MediaTypes": [],
        "StatusCode": 500
      }
    ]
  },
  {
    "ContainingType": "ShoesStore_Project.Controllers.FilterController",
    "Method": "GetPagedFilteredProducts",
    "RelativePath": "api/Filter/GetPagedFilteredProducts",
    "HttpMethod": "GET",
    "IsController": true,
    "Order": 0,
    "Parameters": [
      {
        "Name": "property",
        "Type": "System.String",
        "IsRequired": false
      },
      {
        "Name": "type",
        "Type": "System.String",
        "IsRequired": false
      },
      {
        "Name": "pageNumber",
        "Type": "System.Int32",
        "IsRequired": false
      },
      {
        "Name": "pageSize",
        "Type": "System.Int32",
        "IsRequired": false
      }
    ],
    "ReturnTypes": [
      {
        "Type": "System.Collections.Generic.List\u00601[[Interfaces.DTOs.ProductDTOs.ProductCardDTO, Interfaces, Version=1.0.0.0, Culture=neutral, PublicKeyToken=null]]",
        "MediaTypes": [
          "text/plain",
          "application/json",
          "text/json"
        ],
        "StatusCode": 200
      },
      {
        "Type": "Microsoft.AspNetCore.Mvc.ProblemDetails",
        "MediaTypes": [
          "text/plain",
          "application/json",
          "text/json"
        ],
        "StatusCode": 400
      },
      {
        "Type": "System.Void",
        "MediaTypes": [],
        "StatusCode": 500
      },
      {
        "Type": "Microsoft.AspNetCore.Mvc.ProblemDetails",
        "MediaTypes": [
          "text/plain",
          "application/json",
          "text/json"
        ],
        "StatusCode": 404
      }
    ]
  },
  {
    "ContainingType": "ShoesStore_Project.Controllers.Login.OTP.OTPController",
    "Method": "AddOTP",
    "RelativePath": "api/OTP/AddOTP",
    "HttpMethod": "POST",
    "IsController": true,
    "Order": 0,
    "Parameters": [
      {
        "Name": "Email",
        "Type": "System.String",
        "IsRequired": false
      }
    ],
    "ReturnTypes": [
      {
        "Type": "System.Void",
        "MediaTypes": [],
        "StatusCode": 204
      },
      {
        "Type": "Microsoft.AspNetCore.Mvc.ProblemDetails",
        "MediaTypes": [
          "text/plain",
          "application/json",
          "text/json"
        ],
        "StatusCode": 400
      },
      {
        "Type": "System.Void",
        "MediaTypes": [],
        "StatusCode": 500
      }
    ]
  },
  {
    "ContainingType": "ShoesStore_Project.Controllers.Login.OTP.OTPController",
    "Method": "VerifyOTP",
    "RelativePath": "api/OTP/VerifyOTP",
    "HttpMethod": "GET",
    "IsController": true,
    "Order": 0,
    "Parameters": [
      {
        "Name": "Email",
        "Type": "System.String",
        "IsRequired": false
      },
      {
        "Name": "otp",
        "Type": "System.String",
        "IsRequired": false
      }
    ],
    "ReturnTypes": [
      {
        "Type": "System.Void",
        "MediaTypes": [],
        "StatusCode": 204
      },
      {
        "Type": "Microsoft.AspNetCore.Mvc.ProblemDetails",
        "MediaTypes": [
          "text/plain",
          "application/json",
          "text/json"
        ],
        "StatusCode": 400
      },
      {
        "Type": "System.Void",
        "MediaTypes": [],
        "StatusCode": 500
      }
    ]
  },
  {
    "ContainingType": "ShoesStore_Project.Controllers.ProductController",
    "Method": "AddNewProduct",
    "RelativePath": "api/Product/AddNewProduct",
    "HttpMethod": "POST",
    "IsController": true,
    "Order": 0,
    "Parameters": [
      {
        "Name": "Title",
        "Type": "System.String",
        "IsRequired": false
      },
      {
        "Name": "CategoryID",
        "Type": "System.Int32",
        "IsRequired": false
      },
      {
        "Name": "BrandID",
        "Type": "System.Int32",
        "IsRequired": false
      },
      {
        "Name": "Price",
        "Type": "System.Decimal",
        "IsRequired": false
      },
      {
        "Name": "SizeQuantities",
        "Type": "System.String",
        "IsRequired": false
      },
      {
        "Name": "images",
        "Type": "System.Collections.Generic.List\u00601[[Microsoft.AspNetCore.Http.IFormFile, Microsoft.AspNetCore.Http.Features, Version=8.0.0.0, Culture=neutral, PublicKeyToken=adb9793829ddae60]]",
        "IsRequired": false
      }
    ],
    "ReturnTypes": [
      {
        "Type": "System.Int32",
        "MediaTypes": [
          "text/plain",
          "application/json",
          "text/json"
        ],
        "StatusCode": 200
      },
      {
        "Type": "Microsoft.AspNetCore.Mvc.ProblemDetails",
        "MediaTypes": [
          "text/plain",
          "application/json",
          "text/json"
        ],
        "StatusCode": 400
      },
      {
        "Type": "System.Void",
        "MediaTypes": [],
        "StatusCode": 500
      }
    ]
  },
  {
    "ContainingType": "ShoesStore_Project.Controllers.ProductController",
    "Method": "AddNewSizeQuantity",
    "RelativePath": "api/Product/AddNewSizeQuantity",
    "HttpMethod": "POST",
    "IsController": true,
    "Order": 0,
    "Parameters": [
      {
        "Name": "SQ_Data",
        "Type": "Interfaces.DTOs.InventoryDTOs.ProductSizeQuantityCreateDTO",
        "IsRequired": true
      }
    ],
    "ReturnTypes": [
      {
        "Type": "System.Int32",
        "MediaTypes": [
          "text/plain",
          "application/json",
          "text/json"
        ],
        "StatusCode": 200
      },
      {
        "Type": "System.Void",
        "MediaTypes": [],
        "StatusCode": 500
      },
      {
        "Type": "Microsoft.AspNetCore.Mvc.ProblemDetails",
        "MediaTypes": [
          "text/plain",
          "application/json",
          "text/json"
        ],
        "StatusCode": 404
      }
    ]
  },
  {
    "ContainingType": "ShoesStore_Project.Controllers.ProductController",
    "Method": "DeleteProduct",
    "RelativePath": "api/Product/DeleteProduct/{ProductID}",
    "HttpMethod": "DELETE",
    "IsController": true,
    "Order": 0,
    "Parameters": [
      {
        "Name": "ProductID",
        "Type": "System.Int32",
        "IsRequired": true
      }
    ],
    "ReturnTypes": [
      {
        "Type": "System.Void",
        "MediaTypes": [],
        "StatusCode": 204
      },
      {
        "Type": "Microsoft.AspNetCore.Mvc.ProblemDetails",
        "MediaTypes": [
          "text/plain",
          "application/json",
          "text/json"
        ],
        "StatusCode": 404
      },
      {
        "Type": "System.Void",
        "MediaTypes": [],
        "StatusCode": 500
      }
    ]
  },
  {
    "ContainingType": "ShoesStore_Project.Controllers.ProductController",
    "Method": "GetAllSizeQuantity",
    "RelativePath": "api/Product/GetAllSizeQuantity",
    "HttpMethod": "GET",
    "IsController": true,
    "Order": 0,
    "Parameters": [
      {
        "Name": "ProductID",
        "Type": "System.Int32",
        "IsRequired": false
      }
    ],
    "ReturnTypes": [
      {
        "Type": "System.Collections.Generic.List\u00601[[Interfaces.DTOs.InventoryDTOs.ProductInventoryDTO, Interfaces, Version=1.0.0.0, Culture=neutral, PublicKeyToken=null]]",
        "MediaTypes": [
          "text/plain",
          "application/json",
          "text/json"
        ],
        "StatusCode": 200
      },
      {
        "Type": "System.Void",
        "MediaTypes": [],
        "StatusCode": 500
      },
      {
        "Type": "Microsoft.AspNetCore.Mvc.ProblemDetails",
        "MediaTypes": [
          "text/plain",
          "application/json",
          "text/json"
        ],
        "StatusCode": 404
      }
    ]
  },
  {
    "ContainingType": "ShoesStore_Project.Controllers.ProductController",
    "Method": "GetCountProducts",
    "RelativePath": "api/Product/GetCountProducts",
    "HttpMethod": "GET",
    "IsController": true,
    "Order": 0,
    "Parameters": [],
    "ReturnTypes": [
      {
        "Type": "System.Int32",
        "MediaTypes": [
          "text/plain",
          "application/json",
          "text/json"
        ],
        "StatusCode": 200
      },
      {
        "Type": "System.Void",
        "MediaTypes": [],
        "StatusCode": 500
      }
    ]
  },
  {
    "ContainingType": "ShoesStore_Project.Controllers.ProductController",
    "Method": "GetProduct",
    "RelativePath": "api/Product/GetProduct",
    "HttpMethod": "GET",
    "IsController": true,
    "Order": 0,
    "Parameters": [
      {
        "Name": "ProductID",
        "Type": "System.Int32",
        "IsRequired": false
      }
    ],
    "ReturnTypes": [
      {
        "Type": "Interfaces.DTOs.ProductDTOs.ProductSummaryDTO",
        "MediaTypes": [
          "text/plain",
          "application/json",
          "text/json"
        ],
        "StatusCode": 200
      },
      {
        "Type": "System.Void",
        "MediaTypes": [],
        "StatusCode": 500
      },
      {
        "Type": "Microsoft.AspNetCore.Mvc.ProblemDetails",
        "MediaTypes": [
          "text/plain",
          "application/json",
          "text/json"
        ],
        "StatusCode": 404
      }
    ]
  },
  {
    "ContainingType": "ShoesStore_Project.Controllers.ProductController",
    "Method": "GetProductImages",
    "RelativePath": "api/Product/GetProductImages",
    "HttpMethod": "GET",
    "IsController": true,
    "Order": 0,
    "Parameters": [
      {
        "Name": "ProductID",
        "Type": "System.Int32",
        "IsRequired": false
      }
    ],
    "ReturnTypes": [
      {
        "Type": "System.Collections.Generic.List\u00601[[System.String, System.Private.CoreLib, Version=8.0.0.0, Culture=neutral, PublicKeyToken=7cec85d7bea7798e]]",
        "MediaTypes": [
          "text/plain",
          "application/json",
          "text/json"
        ],
        "StatusCode": 200
      },
      {
        "Type": "System.Void",
        "MediaTypes": [],
        "StatusCode": 500
      },
      {
        "Type": "Microsoft.AspNetCore.Mvc.ProblemDetails",
        "MediaTypes": [
          "text/plain",
          "application/json",
          "text/json"
        ],
        "StatusCode": 404
      }
    ]
  },
  {
    "ContainingType": "ShoesStore_Project.Controllers.ProductController",
    "Method": "GetProductsPaged",
    "RelativePath": "api/Product/GetProductsPaged",
    "HttpMethod": "GET",
    "IsController": true,
    "Order": 0,
    "Parameters": [
      {
        "Name": "pageNumber",
        "Type": "System.Int32",
        "IsRequired": false
      },
      {
        "Name": "pageSize",
        "Type": "System.Int32",
        "IsRequired": false
      }
    ],
    "ReturnTypes": [
      {
        "Type": "System.Collections.Generic.List\u00601[[Interfaces.DTOs.ProductDTOs.ProductDetailsDTO, Interfaces, Version=1.0.0.0, Culture=neutral, PublicKeyToken=null]]",
        "MediaTypes": [
          "text/plain",
          "application/json",
          "text/json"
        ],
        "StatusCode": 200
      },
      {
        "Type": "Microsoft.AspNetCore.Mvc.ProblemDetails",
        "MediaTypes": [
          "text/plain",
          "application/json",
          "text/json"
        ],
        "StatusCode": 400
      },
      {
        "Type": "System.Void",
        "MediaTypes": [],
        "StatusCode": 500
      },
      {
        "Type": "Microsoft.AspNetCore.Mvc.ProblemDetails",
        "MediaTypes": [
          "text/plain",
          "application/json",
          "text/json"
        ],
        "StatusCode": 404
      }
    ]
  },
  {
    "ContainingType": "ShoesStore_Project.Controllers.ProductController",
    "Method": "UpdateProductPrice",
    "RelativePath": "api/Product/UpdateProductPrice",
    "HttpMethod": "PATCH",
    "IsController": true,
    "Order": 0,
    "Parameters": [
      {
        "Name": "ProductID",
        "Type": "System.Int32",
        "IsRequired": false
      },
      {
        "Name": "Price",
        "Type": "System.Decimal",
        "IsRequired": false
      }
    ],
    "ReturnTypes": [
      {
        "Type": "System.Boolean",
        "MediaTypes": [
          "text/plain",
          "application/json",
          "text/json"
        ],
        "StatusCode": 200
      },
      {
        "Type": "Microsoft.AspNetCore.Mvc.ProblemDetails",
        "MediaTypes": [
          "text/plain",
          "application/json",
          "text/json"
        ],
        "StatusCode": 400
      },
      {
        "Type": "Microsoft.AspNetCore.Mvc.ProblemDetails",
        "MediaTypes": [
          "text/plain",
          "application/json",
          "text/json"
        ],
        "StatusCode": 404
      },
      {
        "Type": "System.Void",
        "MediaTypes": [],
        "StatusCode": 500
      }
    ]
  },
  {
    "ContainingType": "ShoesStore_Project.Controllers.ProductController",
    "Method": "UpdateProductQuantity",
    "RelativePath": "api/Product/UpdateProductQuantity",
    "HttpMethod": "PATCH",
    "IsController": true,
    "Order": 0,
    "Parameters": [
      {
        "Name": "StorageID",
        "Type": "System.Int32",
        "IsRequired": false
      },
      {
        "Name": "Quantity",
        "Type": "System.Byte",
        "IsRequired": false
      }
    ],
    "ReturnTypes": [
      {
        "Type": "System.Boolean",
        "MediaTypes": [
          "text/plain",
          "application/json",
          "text/json"
        ],
        "StatusCode": 200
      },
      {
        "Type": "Microsoft.AspNetCore.Mvc.ProblemDetails",
        "MediaTypes": [
          "text/plain",
          "application/json",
          "text/json"
        ],
        "StatusCode": 400
      },
      {
        "Type": "Microsoft.AspNetCore.Mvc.ProblemDetails",
        "MediaTypes": [
          "text/plain",
          "application/json",
          "text/json"
        ],
        "StatusCode": 404
      },
      {
        "Type": "System.Void",
        "MediaTypes": [],
        "StatusCode": 500
      }
    ]
  },
  {
    "ContainingType": "ShoesStore_Project.Controllers.StorageController",
    "Method": "GetSizeQuantity",
    "RelativePath": "api/Storage/GetSizeQuantity",
    "HttpMethod": "GET",
    "IsController": true,
    "Order": 0,
    "Parameters": [
      {
        "Name": "ProductID",
        "Type": "System.Int32",
        "IsRequired": false
      }
    ],
    "ReturnTypes": [
      {
        "Type": "System.Collections.Generic.List\u00601[[Interfaces.DTOs.StorageDTO, Interfaces, Version=1.0.0.0, Culture=neutral, PublicKeyToken=null]]",
        "MediaTypes": [
          "text/plain",
          "application/json",
          "text/json"
        ],
        "StatusCode": 200
      },
      {
        "Type": "System.Void",
        "MediaTypes": [],
        "StatusCode": 500
      },
      {
        "Type": "Microsoft.AspNetCore.Mvc.ProblemDetails",
        "MediaTypes": [
          "text/plain",
          "application/json",
          "text/json"
        ],
        "StatusCode": 404
      }
    ]
  },
  {
    "ContainingType": "ShoesStore_Project.Controllers.Login.Admine.UserController",
    "Method": "AddNewUserAsAdmine",
    "RelativePath": "api/User/AddNewUserAsAdmine",
    "HttpMethod": "POST",
    "IsController": true,
    "Order": 0,
    "Parameters": [
      {
        "Name": "UserName",
        "Type": "System.String",
        "IsRequired": false
      },
      {
        "Name": "Email",
        "Type": "System.String",
        "IsRequired": false
      },
      {
        "Name": "Password",
        "Type": "System.String",
        "IsRequired": false
      },
      {
        "Name": "image",
        "Type": "Microsoft.AspNetCore.Http.IFormFile",
        "IsRequired": false
      }
    ],
    "ReturnTypes": [
      {
        "Type": "System.Int32",
        "MediaTypes": [
          "text/plain",
          "application/json",
          "text/json"
        ],
        "StatusCode": 200
      },
      {
        "Type": "Microsoft.AspNetCore.Mvc.ProblemDetails",
        "MediaTypes": [
          "text/plain",
          "application/json",
          "text/json"
        ],
        "StatusCode": 400
      },
      {
        "Type": "System.Void",
        "MediaTypes": [],
        "StatusCode": 500
      }
    ]
  },
  {
    "ContainingType": "ShoesStore_Project.Controllers.Login.Admine.UserController",
    "Method": "GetAccessToken",
    "RelativePath": "api/User/GetAccessToken",
    "HttpMethod": "GET",
    "IsController": true,
    "Order": 0,
    "Parameters": [
      {
        "Name": "RefreshToken",
        "Type": "System.String",
        "IsRequired": false
      }
    ],
    "ReturnTypes": [
      {
        "Type": "System.String",
        "MediaTypes": [
          "text/plain",
          "application/json",
          "text/json"
        ],
        "StatusCode": 200
      },
      {
        "Type": "Microsoft.AspNetCore.Mvc.ProblemDetails",
        "MediaTypes": [
          "text/plain",
          "application/json",
          "text/json"
        ],
        "StatusCode": 400
      },
      {
        "Type": "System.Void",
        "MediaTypes": [],
        "StatusCode": 500
      },
      {
        "Type": "Microsoft.AspNetCore.Mvc.ProblemDetails",
        "MediaTypes": [
          "text/plain",
          "application/json",
          "text/json"
        ],
        "StatusCode": 401
      }
    ]
  },
  {
    "ContainingType": "ShoesStore_Project.Controllers.Login.Admine.UserController",
    "Method": "GetUser",
    "RelativePath": "api/User/GetUser",
    "HttpMethod": "GET",
    "IsController": true,
    "Order": 0,
    "Parameters": [],
    "ReturnTypes": [
      {
        "Type": "Interfaces.DTOs.UserDTO",
        "MediaTypes": [
          "text/plain",
          "application/json",
          "text/json"
        ],
        "StatusCode": 200
      },
      {
        "Type": "System.Void",
        "MediaTypes": [],
        "StatusCode": 500
      },
      {
        "Type": "Microsoft.AspNetCore.Mvc.ProblemDetails",
        "MediaTypes": [
          "text/plain",
          "application/json",
          "text/json"
        ],
        "StatusCode": 401
      }
    ]
  },
  {
    "ContainingType": "ShoesStore_Project.Controllers.Login.Admine.UserController",
    "Method": "Login",
    "RelativePath": "api/User/Login",
    "HttpMethod": "GET",
    "IsController": true,
    "Order": 0,
    "Parameters": [
      {
        "Name": "Email",
        "Type": "System.String",
        "IsRequired": false
      },
      {
        "Name": "password",
        "Type": "System.String",
        "IsRequired": false
      }
    ],
    "ReturnTypes": [
      {
        "Type": "System.String",
        "MediaTypes": [
          "text/plain",
          "application/json",
          "text/json"
        ],
        "StatusCode": 200
      },
      {
        "Type": "Microsoft.AspNetCore.Mvc.ProblemDetails",
        "MediaTypes": [
          "text/plain",
          "application/json",
          "text/json"
        ],
        "StatusCode": 400
      },
      {
        "Type": "System.Void",
        "MediaTypes": [],
        "StatusCode": 500
      },
      {
        "Type": "Microsoft.AspNetCore.Mvc.ProblemDetails",
        "MediaTypes": [
          "text/plain",
          "application/json",
          "text/json"
        ],
        "StatusCode": 401
      }
    ]
  }
]